archerqueen/__init__.py
archerqueen/experiment5.py
archerqueen/experiment6.py
archerqueen/experiment7.py
archerqueen/experiment8.py
archerqueen/main.py
archerqueen-0.2.0.dist-info/METADATA
archerqueen-0.2.0.dist-info/WHEEL
archerqueen-0.2.0.dist-info/entry_points.txt
archerqueen-0.2.0.dist-info/top_level.txt
archerqueen-0.2.0.dist-info/RECORD
