Metadata-Version: 2.1
Name: archerqueen
Version: 0.2.0
Summary: Advanced data analysis toolkit
Author: Incineroar
Requires-Python: >=3.6
Requires-Dist: pandas
Requires-Dist: matplotlib
Requires-Dist: scikit-learn
Requires-Dist: nltk
Requires-Dist: wordcloud
Requires-Dist: seaborn
Requires-Dist: textblob
Requires-Dist: networkx
